LICENSE.txt
MANIFEST.in
README.md
setup.cfg
setup.py
CutPdfFun/CutPDf.pyd
CutPdfFun/__init__.py
CutPdfFun/cutPdfFun.exe
CutPdfFun/url.db
CutPdfFun.egg-info/PKG-INFO
CutPdfFun.egg-info/SOURCES.txt
CutPdfFun.egg-info/dependency_links.txt
CutPdfFun.egg-info/requires.txt
CutPdfFun.egg-info/top_level.txt