Metadata-Version: 2.1
Name: CutPdfFun
Version: 1.0.7
Summary: Dynamsoft Barcode Reader Python project
Home-page: https://mail.163.com/js6/main.jsp?sid=PAlGWIYldfIQjfQTFYllFVEyKXidwtNk&df=mail163_letter#module=welcome.WelcomeModule%7C%7B%7D
Author: wangweidong
Author-email: 17891967090@163.com
License: Apache
Classifier: License :: OSI Approved :: Apache Software License
Classifier: Natural Language :: English
Classifier: Operating System :: OS Independent
Classifier: Programming Language :: Python
Classifier: Topic :: Software Development :: Libraries :: Python Modules
Requires-Python: >=3.7
License-File: LICENSE.txt
